jta/__init__.py
jta/qsutil/__init__.py
jta/qsutil/parse.py
jta.qsutil-0.1.1.dist-info/METADATA
jta.qsutil-0.1.1.dist-info/RECORD
jta.qsutil-0.1.1.dist-info/WHEEL
jta.qsutil-0.1.1.dist-info/top_level.txt
